<?xml version="1.0" encoding="UTF-8" standalone="yes"?>
<tree>
  <declarations>
    <attributeDecl name="name" type="String"/>
  </declarations>
  <branch>
    <attribute name="name" value="Nagetiere"/>
    <branch>
      <attribute name="name" value=""/>
      <branch>
        <attribute name="name" value="Mäuseverwandte"/>
        <branch>
          <attribute name="name" value="Mäuseartige"/>
          <branch>
            <attribute name="name" value=""/>
            <branch>
              <attribute name="name" value="Eumuroida"/>
              <branch>
                <attribute name="name" value=""/>
                <branch>
                  <attribute name="name" value=""/>
                  <branch>
                    <attribute name="name" value="Wühler"/>
                    <branch>
                      <attribute name="name" value=""/>
                      <branch>
                        <attribute name="name" value="Hamster"/>
                      </branch>
                      <branch>
                        <attribute name="name" value="Wühlmäuse"/>
                      </branch>
                    </branch>
                    <branch>
                      <attribute name="name" value=""/>
                      <branch>
                        <attribute name="name" value="Neotominae"/>
                      </branch>
                      <branch>
                        <attribute name="name" value=""/>
                        <branch>
                          <attribute name="name" value="Sigmodontinae"/>
                          <branch>
                            <attribute name="name" value="Oryzomyalia"/>
                            <branch>
                              <attribute name="name" value="Thomasomyine group and Sigmodontinae incertae sedis"/>
                              <branch>
                                <attribute name="name" value="Ruschi-Ratte"/>
                              </branch>
                              <branch>
                                <attribute name="name" value="Andenmäuse"/>
                              </branch>
                              <branch>
                                <attribute name="name" value="Kolumbianische Waldmaus"/>
                              </branch>
                              <branch>
                                <attribute name="name" value="Rio-de-Janeiro-Ratte"/>
                              </branch>
                              <branch>
                                <attribute name="name" value="Brasilianische Baummäuse"/>
                              </branch>
                              <branch>
                                <attribute name="name" value=""/>
                                <branch>
                                  <attribute name="name" value="Klettermäuse"/>
                                </branch>
                                <branch>
                                  <attribute name="name" value="Paramo-Mäuse"/>
                                </branch>
                              </branch>
                              <branch>
                                <attribute name="name" value="Wilfred-Maus"/>
                              </branch>
                            </branch>
                            <branch>
                              <attribute name="name" value="Wiedomyini"/>
                              <branch>
                                <attribute name="name" value="Rotnasenmaus"/>
                              </branch>
                            </branch>
                            <branch>
                              <attribute name="name" value="Oryzomyini"/>
                              <branch>
                                <attribute name="name" value="Galápagos-Riesenratte"/>
                              </branch>
                              <branch>
                                <attribute name="name" value="Zuckermäuse"/>
                              </branch>
                              <branch>
                                <attribute name="name" value="Amerikanische Stachelmäuse"/>
                              </branch>
                              <branch>
                                <attribute name="name" value=""/>
                                <branch>
                                  <attribute name="name" value=""/>
                                  <branch>
                                    <attribute name="name" value=""/>
                                    <branch>
                                      <attribute name="name" value="Handleyomys"/>
                                    </branch>
                                    <branch>
                                      <attribute name="name" value=""/>
                                      <branch>
                                        <attribute name="name" value="Zweifarb-Reisratten"/>
                                      </branch>
                                    </branch>
                                  </branch>
                                </branch>
                                <branch>
                                  <attribute name="name" value=""/>
                                  <branch>
                                    <attribute name="name" value=""/>
                                    <branch>
                                      <attribute name="name" value="Zwergreisratten"/>
                                    </branch>
                                    <branch>
                                      <attribute name="name" value=""/>
                                      <branch>
                                        <attribute name="name" value="Stachelreisratten"/>
                                      </branch>
                                      <branch>
                                        <attribute name="name" value=""/>
                                        <branch>
                                          <attribute name="name" value="Kleinstreisratten"/>
                                        </branch>
                                      </branch>
                                    </branch>
                                    <branch>
                                      <attribute name="name" value="Brasilia-Ratte"/>
                                    </branch>
                                  </branch>
                                  <branch>
                                    <attribute name="name" value=""/>
                                    <branch>
                                      <attribute name="name" value=""/>
                                      <branch>
                                        <attribute name="name" value=""/>
                                        <branch>
                                          <attribute name="name" value=""/>
                                          <branch>
                                            <attribute name="name" value="Sumpfratten"/>
                                          </branch>
                                          <branch>
                                            <attribute name="name" value="Brasilianische Reisratte"/>
                                          </branch>
                                        </branch>
                                        <branch>
                                          <attribute name="name" value="Lund-Wasserratte"/>
                                        </branch>
                                        <branch>
                                          <attribute name="name" value="Fernando-de-Noronha-Ratte"/>
                                        </branch>
                                      </branch>
                                      <branch>
                                        <attribute name="name" value=""/>
                                        <branch>
                                          <attribute name="name" value="Reisratten"/>
                                        </branch>
                                        <branch>
                                          <attribute name="name" value=""/>
                                          <branch>
                                            <attribute name="name" value="Neotropische Wasserratten"/>
                                          </branch>
                                          <branch>
                                            <attribute name="name" value="Ucayali-Wasserratte"/>
                                          </branch>
                                        </branch>
                                        <branch>
                                          <attribute name="name" value=""/>
                                          <branch>
                                            <attribute name="name" value=""/>
                                            <branch>
                                              <attribute name="name" value="Galápagos-Reisratten"/>
                                            </branch>
                                          </branch>
                                          <branch>
                                            <attribute name="name" value=""/>
                                            <branch>
                                              <attribute name="name" value="Karibische Riesenreisratten"/>
                                            </branch>
                                            <branch>
                                              <attribute name="name" value=""/>
                                              <branch>
                                                <attribute name="name" value="Dunkle Reisratten"/>
                                              </branch>
                                              <branch>
                                                <attribute name="name" value="Alfaro-Wasserratte"/>
                                              </branch>
                                            </branch>
                                          </branch>
                                        </branch>
                                      </branch>
                                    </branch>
                                  </branch>
                                </branch>
                              </branch>
                            </branch>
                            <branch>
                              <attribute name="name" value="Phyllotini"/>
                              <branch>
                                <attribute name="name" value="Vespermäuse"/>
                                <branch>
                                  <attribute name="name" value=""/>
                                  <branch>
                                    <attribute name="name" value=""/>
                                    <branch>
                                      <attribute name="name" value="Vespermaus"/>
                                    </branch>
                                  </branch>
                                </branch>
                              </branch>
                              <branch>
                                <attribute name="name" value=""/>
                                <branch>
                                  <attribute name="name" value="Hochland-Wüstenmäuse"/>
                                </branch>
                                <branch>
                                  <attribute name="name" value=""/>
                                  <branch>
                                    <attribute name="name" value="Graomys"/>
                                  </branch>
                                  <branch>
                                    <attribute name="name" value=""/>
                                    <branch>
                                      <attribute name="name" value="Blattohrmäuse"/>
                                      <branch>
                                        <attribute name="name" value=""/>
                                        <branch>
                                          <attribute name="name" value=""/>
                                          <branch>
                                            <attribute name="name" value=""/>
                                            <branch>
                                              <attribute name="name" value="Phyllotis darwini species group"/>
                                              <branch>
                                                <attribute name="name" value=""/>
                                                <branch>
                                                  <attribute name="name" value="Osgood-Blattohrmaus"/>
                                                </branch>
                                              </branch>
                                            </branch>
                                          </branch>
                                        </branch>
                                      </branch>
                                    </branch>
                                    <branch>
                                      <attribute name="name" value=""/>
                                      <branch>
                                        <attribute name="name" value="Auliscomys group"/>
                                        <branch>
                                          <attribute name="name" value="Großohrmäuse"/>
                                        </branch>
                                        <branch>
                                          <attribute name="name" value="Garlepp-Maus"/>
                                        </branch>
                                      </branch>
                                      <branch>
                                        <attribute name="name" value="Loxodontomys"/>
                                      </branch>
                                    </branch>
                                    <branch>
                                      <attribute name="name" value="Altiplano-Chinchillamaus"/>
                                    </branch>
                                  </branch>
                                  <branch>
                                    <attribute name="name" value="Salinomys delicatus"/>
                                  </branch>
                                  <branch>
                                    <attribute name="name" value="Tapecomys primus"/>
                                  </branch>
                                </branch>
                                <branch>
                                  <attribute name="name" value="Chaco-Mäuse"/>
                                </branch>
                              </branch>
                            </branch>
                            <branch>
                              <attribute name="name" value="Andenmaus"/>
                            </branch>
                            <branch>
                              <attribute name="name" value="Puna-Mäuse"/>
                            </branch>
                            <branch>
                              <attribute name="name" value=""/>
                              <branch>
                                <attribute name="name" value="Kaninchenratten"/>
                              </branch>
                            </branch>
                            <branch>
                              <attribute name="name" value="Chile-Ratte"/>
                            </branch>
                            <branch>
                              <attribute name="name" value="Patagonische Chinchillamäuse"/>
                            </branch>
                            <branch>
                              <attribute name="name" value="Anden-Sumpfratte"/>
                            </branch>
                            <branch>
                              <attribute name="name" value="Abrothicine group"/>
                              <branch>
                                <attribute name="name" value=""/>
                                <branch>
                                  <attribute name="name" value="Anden-Feldmäuse"/>
                                </branch>
                                <branch>
                                  <attribute name="name" value="Anden-Feldmäuse"/>
                                </branch>
                              </branch>
                              <branch>
                                <attribute name="name" value=""/>
                                <branch>
                                  <attribute name="name" value="Große Langkrallenmäuse"/>
                                </branch>
                                <branch>
                                  <attribute name="name" value="Pearson-Langkrallenmaus"/>
                                </branch>
                                <branch>
                                  <attribute name="name" value="Langkrallen-Maulwurfsmaus"/>
                                </branch>
                                <branch>
                                  <attribute name="name" value="Edwards-Langkrallenmaus"/>
                                </branch>
                              </branch>
                            </branch>
                            <branch>
                              <attribute name="name" value="Akodontini"/>
                              <branch>
                                <attribute name="name" value=""/>
                                <branch>
                                  <attribute name="name" value=""/>
                                  <branch>
                                    <attribute name="name" value=""/>
                                    <branch>
                                      <attribute name="name" value="Necromys"/>
                                    </branch>
                                  </branch>
                                  <branch>
                                    <attribute name="name" value="Cerrado-Mäuse"/>
                                  </branch>
                                </branch>
                                <branch>
                                  <attribute name="name" value="Andenratte"/>
                                </branch>
                              </branch>
                              <branch>
                                <attribute name="name" value="Brasilianische Spitzmausratte"/>
                              </branch>
                              <branch>
                                <attribute name="name" value="Maulwurfsmäuse"/>
                              </branch>
                              <branch>
                                <attribute name="name" value="Grabmäuse"/>
                              </branch>
                              <branch>
                                <attribute name="name" value="Karminnasenratten"/>
                              </branch>
                              <branch>
                                <attribute name="name" value=""/>
                                <branch>
                                  <attribute name="name" value="Scapteromys"/>
                                </branch>
                                <branch>
                                  <attribute name="name" value="Südamerikanische Riesenratten"/>
                                </branch>
                              </branch>
                            </branch>
                            <branch>
                              <attribute name="name" value="Atlantische Waldratten"/>
                            </branch>
                            <branch>
                              <attribute name="name" value="Juliomys"/>
                            </branch>
                          </branch>
                          <branch>
                            <attribute name="name" value=""/>
                            <branch>
                              <attribute name="name" value="Sigmodontini"/>
                              <branch>
                                <attribute name="name" value=""/>
                                <branch>
                                  <attribute name="name" value="Gelbnasen-Baumwollratte"/>
                                </branch>
                                <branch>
                                  <attribute name="name" value=""/>
                                  <branch>
                                    <attribute name="name" value="Südliche Baumwollratte"/>
                                  </branch>
                                </branch>
                              </branch>
                            </branch>
                            <branch>
                              <attribute name="name" value="Fischratten"/>
                              <branch>
                                <attribute name="name" value=""/>
                                <branch>
                                  <attribute name="name" value=""/>
                                  <branch>
                                    <attribute name="name" value=""/>
                                    <branch>
                                      <attribute name="name" value=""/>
                                      <branch>
                                        <attribute name="name" value="Ecuador-Fischratte"/>
                                      </branch>
                                      <branch>
                                        <attribute name="name" value=""/>
                                        <branch>
                                          <attribute name="name" value="Eigentliche Fischratten"/>
                                        </branch>
                                        <branch>
                                          <attribute name="name" value="Mittelamerikanische Wassermäuse"/>
                                        </branch>
                                      </branch>
                                    </branch>
                                  </branch>
                                </branch>
                              </branch>
                            </branch>
                          </branch>
                        </branch>
                        <branch>
                          <attribute name="name" value="Tylomyinae"/>
                          <branch>
                            <attribute name="name" value="Vesperratte"/>
                          </branch>
                          <branch>
                            <attribute name="name" value="Yucatán-Vesperratte"/>
                          </branch>
                          <branch>
                            <attribute name="name" value="Kletterratten"/>
                          </branch>
                          <branch>
                            <attribute name="name" value="Großohr-Kletterratte"/>
                          </branch>
                        </branch>
                      </branch>
                    </branch>
                  </branch>
                  <branch>
                    <attribute name="name" value="Langschwanzmäuse"/>
                    <branch>
                      <attribute name="name" value=""/>
                      <branch>
                        <attribute name="name" value="Altweltmäuse"/>
                        <branch>
                          <attribute name="name" value="Phloeomyini"/>
                          <branch>
                            <attribute name="name" value="Riesenborkenratten"/>
                          </branch>
                          <branch>
                            <attribute name="name" value="Philippinen-Haarschwanzratten"/>
                          </branch>
                          <branch>
                            <attribute name="name" value="Borkenkletterer"/>
                          </branch>
                          <branch>
                            <attribute name="name" value="Luzon-Baumratten"/>
                          </branch>
                        </branch>
                        <branch>
                          <attribute name="name" value=""/>
                          <branch>
                            <attribute name="name" value="Rattini"/>
                            <branch>
                              <attribute name="name" value=""/>
                              <branch>
                                <attribute name="name" value=""/>
                                <branch>
                                  <attribute name="name" value="Ratten"/>
                                </branch>
                                <branch>
                                  <attribute name="name" value="Weißzahnratten"/>
                                </branch>
                                <branch>
                                  <attribute name="name" value="Tarsomys"/>
                                </branch>
                                <branch>
                                  <attribute name="name" value="Limnomys"/>
                                </branch>
                                <branch>
                                  <attribute name="name" value="Luzon-Breitzahnratte"/>
                                </branch>
                                <branch>
                                  <attribute name="name" value="Philippinen-Moosmäuse"/>
                                </branch>
                                <branch>
                                  <attribute name="name" value="Bandikutratten"/>
                                </branch>
                                <branch>
                                  <attribute name="name" value="Sunda-Riesenratten"/>
                                </branch>
                              </branch>
                              <branch>
                                <attribute name="name" value=""/>
                                <branch>
                                  <attribute name="name" value="Weißbauchratten"/>
                                </branch>
                                <branch>
                                  <attribute name="name" value=""/>
                                  <branch>
                                    <attribute name="name" value="Millard-Ratte"/>
                                  </branch>
                                  <branch>
                                    <attribute name="name" value="Langschwanz-Riesenratten"/>
                                  </branch>
                                </branch>
                              </branch>
                            </branch>
                            <branch>
                              <attribute name="name" value="Rajah-Ratten"/>
                            </branch>
                          </branch>
                          <branch>
                            <attribute name="name" value=""/>
                            <branch>
                              <attribute name="name" value=""/>
                              <branch>
                                <attribute name="name" value=""/>
                                <branch>
                                  <attribute name="name" value=""/>
                                  <branch>
                                    <attribute name="name" value=""/>
                                    <branch>
                                      <attribute name="name" value="Apodemini"/>
                                      <branch>
                                        <attribute name="name" value="Ryukyu-Stachelratten"/>
                                      </branch>
                                      <branch>
                                        <attribute name="name" value="Waldmäuse"/>
                                      </branch>
                                    </branch>
                                  </branch>
                                  <branch>
                                    <attribute name="name" value=""/>
                                    <branch>
                                      <attribute name="name" value="Praomyini"/>
                                      <branch>
                                        <attribute name="name" value="Afrikanische Weichratten"/>
                                      </branch>
                                      <branch>
                                        <attribute name="name" value="Vielzitzenmäuse"/>
                                      </branch>
                                      <branch>
                                        <attribute name="name" value="Breitkopfmäuse"/>
                                      </branch>
                                      <branch>
                                        <attribute name="name" value="Afrikanische Waldmäuse"/>
                                      </branch>
                                      <branch>
                                        <attribute name="name" value="Myomyscus"/>
                                      </branch>
                                      <branch>
                                        <attribute name="name" value="Afrikanische Wasserratte"/>
                                      </branch>
                                      <branch>
                                        <attribute name="name" value="Afrikanische Rauchmaus"/>
                                      </branch>
                                    </branch>
                                  </branch>
                                </branch>
                                <branch>
                                  <attribute name="name" value="Langschwanz-Klettermäuse"/>
                                </branch>
                              </branch>
                              <branch>
                                <attribute name="name" value=""/>
                                <branch>
                                  <attribute name="name" value="Arvicanthine group"/>
                                  <branch>
                                    <attribute name="name" value="Arvicanthini"/>
                                    <branch>
                                      <attribute name="name" value="Streifengrasmäuse"/>
                                    </branch>
                                    <branch>
                                      <attribute name="name" value="Kusuratten"/>
                                    </branch>
                                    <branch>
                                      <attribute name="name" value="Afrikanische Striemen-Grasmäuse"/>
                                    </branch>
                                    <branch>
                                      <attribute name="name" value="Afrikanische Buschratten"/>
                                    </branch>
                                    <branch>
                                      <attribute name="name" value=""/>
                                      <branch>
                                        <attribute name="name" value="Zielratte"/>
                                      </branch>
                                      <branch>
                                        <attribute name="name" value="Streifenmäuse"/>
                                      </branch>
                                    </branch>
                                    <branch>
                                      <attribute name="name" value="Harrington-Ratten"/>
                                    </branch>
                                    <branch>
                                      <attribute name="name" value="Furchenzahn-Bachratten"/>
                                    </branch>
                                    <branch>
                                      <attribute name="name" value="Afrikanische Furchenzahnratten"/>
                                    </branch>
                                    <branch>
                                      <attribute name="name" value="Akazienmäuse"/>
                                    </branch>
                                    <branch>
                                      <attribute name="name" value="Rotnasenratten"/>
                                    </branch>
                                    <branch>
                                      <attribute name="name" value="Akazienratten"/>
                                    </branch>
                                  </branch>
                                  <branch>
                                    <attribute name="name" value="Otomyini"/>
                                    <branch>
                                      <attribute name="name" value="Lamellenzahnratten"/>
                                    </branch>
                                    <branch>
                                      <attribute name="name" value="Karru-Ratten"/>
                                    </branch>
                                  </branch>
                                </branch>
                              </branch>
                            </branch>
                            <branch>
                              <attribute name="name" value=""/>
                              <branch>
                                <attribute name="name" value="Hydromyini"/>
                                <branch>
                                  <attribute name="name" value="Philippine Old Endemics II"/>
                                  <branch>
                                    <attribute name="name" value="Shrew rats"/>
                                    <branch>
                                      <attribute name="name" value="Luzon-Streifenratten"/>
                                    </branch>
                                    <branch>
                                      <attribute name="name" value="Archboldomys"/>
                                    </branch>
                                    <branch>
                                      <attribute name="name" value="Nasenratten"/>
                                    </branch>
                                  </branch>
                                  <branch>
                                    <attribute name="name" value="Apomys"/>
                                  </branch>
                                </branch>
                                <branch>
                                  <attribute name="name" value="New Guinea group"/>
                                  <branch>
                                    <attribute name="name" value="Weißohr-Riesenratten"/>
                                  </branch>
                                  <branch>
                                    <attribute name="name" value="Hörnchenzahnratte"/>
                                  </branch>
                                  <branch>
                                    <attribute name="name" value=""/>
                                    <branch>
                                      <attribute name="name" value="Chiruromys"/>
                                    </branch>
                                    <branch>
                                      <attribute name="name" value="Greifschwanzratten"/>
                                    </branch>
                                  </branch>
                                  <branch>
                                    <attribute name="name" value="Neuguinea-Bürstenratten"/>
                                  </branch>
                                  <branch>
                                    <attribute name="name" value="Neuguinea-Kleinzahnratten"/>
                                  </branch>
                                  <branch>
                                    <attribute name="name" value="Riesenbaumratten"/>
                                  </branch>
                                </branch>
                                <branch>
                                  <attribute name="name" value=""/>
                                  <branch>
                                    <attribute name="name" value=""/>
                                    <branch>
                                      <attribute name="name" value="Australische Häschenratten"/>
                                    </branch>
                                    <branch>
                                      <attribute name="name" value="Australische Kaninchenratten"/>
                                    </branch>
                                    <branch>
                                      <attribute name="name" value="Australische Baumratten"/>
                                    </branch>
                                  </branch>
                                  <branch>
                                    <attribute name="name" value=""/>
                                    <branch>
                                      <attribute name="name" value="Australische Breitzahnratte"/>
                                    </branch>
                                    <branch>
                                      <attribute name="name" value="Australische Mäuse"/>
                                    </branch>
                                    <branch>
                                      <attribute name="name" value="Australische Hüpfmäuse"/>
                                    </branch>
                                  </branch>
                                  <branch>
                                    <attribute name="name" value="Australische Dickschwanzratten"/>
                                  </branch>
                                  <branch>
                                    <attribute name="name" value="Mosaikschwanz-Riesenratten"/>
                                  </branch>
                                  <branch>
                                    <attribute name="name" value="Leggadina"/>
                                  </branch>
                                  <branch>
                                    <attribute name="name" value=""/>
                                    <branch>
                                      <attribute name="name" value="Schwimmratten"/>
                                    </branch>
                                    <branch>
                                      <attribute name="name" value="Bergschwimmratte"/>
                                    </branch>
                                  </branch>
                                  <branch>
                                    <attribute name="name" value=""/>
                                    <branch>
                                      <attribute name="name" value="Shaw-Mayer-Maus"/>
                                    </branch>
                                    <branch>
                                      <attribute name="name" value="Neuguinea-Moosmäuse"/>
                                    </branch>
                                  </branch>
                                  <branch>
                                    <attribute name="name" value="Falsche Schwimmratte"/>
                                  </branch>
                                  <branch>
                                    <attribute name="name" value="Monckton-Schwimmratte"/>
                                  </branch>
                                  <branch>
                                    <attribute name="name" value="Neuguinea-Wasserratten"/>
                                  </branch>
                                  <branch>
                                    <attribute name="name" value=""/>
                                    <branch>
                                      <attribute name="name" value="Nacktschwanzratten"/>
                                    </branch>
                                    <branch>
                                      <attribute name="name" value="Mosaikschwanzratten"/>
                                    </branch>
                                  </branch>
                                </branch>
                              </branch>
                              <branch>
                                <attribute name="name" value="Pinselschwanz-Baummäuse"/>
                              </branch>
                            </branch>
                          </branch>
                        </branch>
                      </branch>
                      <branch>
                        <attribute name="name" value=""/>
                        <branch>
                          <attribute name="name" value="Rennmäuse"/>
                        </branch>
                        <branch>
                          <attribute name="name" value="Deomyinae"/>
                          <branch>
                            <attribute name="name" value="Stachelmäuse"/>
                          </branch>
                          <branch>
                            <attribute name="name" value="Bürstenhaarmäuse"/>
                          </branch>
                          <branch>
                            <attribute name="name" value="Weißbauch-Bürstenhaarmaus"/>
                          </branch>
                        </branch>
                      </branch>
                    </branch>
                  </branch>
                </branch>
                <branch>
                  <attribute name="name" value="Nesomyidae"/>
                  <branch>
                    <attribute name="name" value=""/>
                    <branch>
                      <attribute name="name" value=""/>
                      <branch>
                        <attribute name="name" value="Baummäuse"/>
                      </branch>
                      <branch>
                        <attribute name="name" value="Hamsterratten"/>
                      </branch>
                    </branch>
                    <branch>
                      <attribute name="name" value=""/>
                      <branch>
                        <attribute name="name" value="Afrikanischer Hamster"/>
                      </branch>
                    </branch>
                  </branch>
                  <branch>
                    <attribute name="name" value="Madagaskar-Ratten"/>
                  </branch>
                </branch>
              </branch>
            </branch>
            <branch>
              <attribute name="name" value="Spalacidae"/>
              <branch>
                <attribute name="name" value=""/>
                <branch>
                  <attribute name="name" value="Wurzelratten"/>
                </branch>
                <branch>
                  <attribute name="name" value="Blindmäuse"/>
                </branch>
              </branch>
              <branch>
                <attribute name="name" value="Blindmulle"/>
              </branch>
            </branch>
          </branch>
          <branch>
            <attribute name="name" value="Stachelbilche"/>
          </branch>
        </branch>
      </branch>
      <branch>
        <attribute name="name" value="Dornschwanzhörnchenverwandte"/>
      </branch>
      <branch>
        <attribute name="name" value="Biberverwandte"/>
        <branch>
          <attribute name="name" value="Taschennager"/>
        </branch>
        <branch>
          <attribute name="name" value="Biber"/>
        </branch>
      </branch>
    </branch>
    <branch>
      <attribute name="name" value="Hörnchenverwandte"/>
      <branch>
        <attribute name="name" value=""/>
        <branch>
          <attribute name="name" value="Stummelschwanzhörnchen"/>
        </branch>
        <branch>
          <attribute name="name" value="Hörnchen"/>
          <branch>
            <attribute name="name" value=""/>
            <branch>
              <attribute name="name" value="Schönhörnchen"/>
              <branch>
                <attribute name="name" value="Callosciurini"/>
                <branch>
                  <attribute name="name" value="Echte Schönhörnchen"/>
                </branch>
                <branch>
                  <attribute name="name" value="Rotwangenhörnchen"/>
                </branch>
                <branch>
                  <attribute name="name" value="Asiatische Zwerghörnchen"/>
                </branch>
                <branch>
                  <attribute name="name" value="Borneo-Zwerghörnchen"/>
                </branch>
                <branch>
                  <attribute name="name" value="Ferkelhörnchen"/>
                </branch>
                <branch>
                  <attribute name="name" value="Schwarzstreifenhörnchen"/>
                </branch>
                <branch>
                  <attribute name="name" value="Menetes"/>
                </branch>
                <branch>
                  <attribute name="name" value="Braunes Zwerghörnchen"/>
                </branch>
                <branch>
                  <attribute name="name" value="Sulawesi-Zwerghörnchen"/>
                </branch>
                <branch>
                  <attribute name="name" value="Sulawesi-Riesenhörnchen"/>
                </branch>
                <branch>
                  <attribute name="name" value="Baumstreifenhörnchen"/>
                </branch>
                <branch>
                  <attribute name="name" value="Sunda-Baumhörnchen"/>
                </branch>
              </branch>
              <branch>
                <attribute name="name" value="Protoxerini"/>
              </branch>
            </branch>
            <branch>
              <attribute name="name" value="Erdhörnchen"/>
              <branch>
                <attribute name="name" value=""/>
                <branch>
                  <attribute name="name" value="Echte Erdhörnchen"/>
                  <branch>
                    <attribute name="name" value=""/>
                    <branch>
                      <attribute name="name" value="Ziesel"/>
                    </branch>
                    <branch>
                      <attribute name="name" value="Präriehunde"/>
                    </branch>
                    <branch>
                      <attribute name="name" value="Murmeltiere"/>
                      <branch>
                        <attribute name="name" value=""/>
                        <branch>
                          <attribute name="name" value=""/>
                          <branch>
                            <attribute name="name" value=""/>
                            <branch>
                              <attribute name="name" value=""/>
                              <branch>
                                <attribute name="name" value="Sibirisches Murmeltier"/>
                              </branch>
                            </branch>
                            <branch>
                              <attribute name="name" value="Schwarzhut-Murmeltier"/>
                            </branch>
                          </branch>
                          <branch>
                            <attribute name="name" value=""/>
                            <branch>
                              <attribute name="name" value="Steppenmurmeltier"/>
                            </branch>
                            <branch>
                              <attribute name="name" value="Graues Murmeltier"/>
                            </branch>
                          </branch>
                        </branch>
                        <branch>
                          <attribute name="name" value="Alaska-Murmeltier"/>
                        </branch>
                        <branch>
                          <attribute name="name" value=""/>
                          <branch>
                            <attribute name="name" value="Langschwanzmurmeltier"/>
                          </branch>
                          <branch>
                            <attribute name="name" value="Menzbiers Murmeltier"/>
                          </branch>
                        </branch>
                        <branch>
                          <attribute name="name" value="Alpenmurmeltier"/>
                        </branch>
                        <branch>
                          <attribute name="name" value="Waldmurmeltier"/>
                        </branch>
                      </branch>
                      <branch>
                        <attribute name="name" value=""/>
                        <branch>
                          <attribute name="name" value="Gelbbauchmurmeltier"/>
                        </branch>
                        <branch>
                          <attribute name="name" value=""/>
                          <branch>
                            <attribute name="name" value="Eisgraues Murmeltier"/>
                          </branch>
                          <branch>
                            <attribute name="name" value="Vancouver-Murmeltier"/>
                          </branch>
                        </branch>
                        <branch>
                          <attribute name="name" value="Olympisches Murmeltier"/>
                        </branch>
                      </branch>
                    </branch>
                    <branch>
                      <attribute name="name" value="Antilopenziesel"/>
                    </branch>
                  </branch>
                  <branch>
                    <attribute name="name" value="Streifenhörnchen"/>
                  </branch>
                  <branch>
                    <attribute name="name" value="Chinesische Rothörnchen"/>
                  </branch>
                </branch>
                <branch>
                  <attribute name="name" value="Protoxerini"/>
                  <branch>
                    <attribute name="name" value="Protoxerina"/>
                    <branch>
                      <attribute name="name" value="Afrikanisches Palmenhörnchen"/>
                    </branch>
                    <branch>
                      <attribute name="name" value="Sonnenhörnchen"/>
                    </branch>
                    <branch>
                      <attribute name="name" value="Ölpalmenhörnchen"/>
                    </branch>
                  </branch>
                  <branch>
                    <attribute name="name" value="Funisciurina"/>
                    <branch>
                      <attribute name="name" value="Rotschenkelhörnchen"/>
                    </branch>
                    <branch>
                      <attribute name="name" value="Afrikanisches Zwerghörnchen"/>
                    </branch>
                    <branch>
                      <attribute name="name" value="Afrikanische Buschhörnchen"/>
                    </branch>
                  </branch>
                </branch>
              </branch>
              <branch>
                <attribute name="name" value="Borstenhörnchen"/>
                <branch>
                  <attribute name="name" value="Atlashörnchen"/>
                </branch>
                <branch>
                  <attribute name="name" value="Zieselmaus"/>
                </branch>
                <branch>
                  <attribute name="name" value="Afrikanische Borstenhörnchen"/>
                  <branch>
                    <attribute name="name" value="Gestreiftes Borstenhörnchen"/>
                  </branch>
                  <branch>
                    <attribute name="name" value="Kap-Borstenhörnchen"/>
                  </branch>
                  <branch>
                    <attribute name="name" value="Kaokoveld-Borstenhörnchen"/>
                  </branch>
                  <branch>
                    <attribute name="name" value="Schlichtborstenhörnchen"/>
                  </branch>
                </branch>
              </branch>
            </branch>
            <branch>
              <attribute name="name" value="Baum- und Gleithörnchen"/>
              <branch>
                <attribute name="name" value=""/>
                <branch>
                  <attribute name="name" value="Baumhörnchen"/>
                  <branch>
                    <attribute name="name" value="Borneo-Hörnchen"/>
                  </branch>
                  <branch>
                    <attribute name="name" value=""/>
                    <branch>
                      <attribute name="name" value="Sciurus"/>
                    </branch>
                    <branch>
                      <attribute name="name" value="Microsciurini"/>
                      <branch>
                        <attribute name="name" value="Neuweltliche Zwerghörnchen"/>
                      </branch>
                      <branch>
                        <attribute name="name" value="Mittelamerikanisches Berghörnchen"/>
                      </branch>
                    </branch>
                  </branch>
                </branch>
              </branch>
              <branch>
                <attribute name="name" value="Gleithörnchen"/>
                <branch>
                  <attribute name="name" value="Furchenzahn-Gleithörnchen"/>
                </branch>
                <branch>
                  <attribute name="name" value="Schwarze Gleithörnchen"/>
                </branch>
                <branch>
                  <attribute name="name" value="Haarfuß-Gleithörnchen"/>
                </branch>
                <branch>
                  <attribute name="name" value="Biswamoyopterus"/>
                </branch>
                <branch>
                  <attribute name="name" value="Felsgleithörnchen"/>
                </branch>
                <branch>
                  <attribute name="name" value="Neuweltliche Gleithörnchen"/>
                </branch>
                <branch>
                  <attribute name="name" value="Pfeilschwanz-Gleithörnchen"/>
                </branch>
                <branch>
                  <attribute name="name" value="Iomys"/>
                </branch>
                <branch>
                  <attribute name="name" value="Kleinstgleithörnchen"/>
                </branch>
                <branch>
                  <attribute name="name" value="Riesengleithörnchen"/>
                </branch>
                <branch>
                  <attribute name="name" value="Zwerggleithörnchen"/>
                </branch>
                <branch>
                  <attribute name="name" value="Echte Gleithörnchen"/>
                </branch>
                <branch>
                  <attribute name="name" value="Rauchgraues Gleithörnchen"/>
                </branch>
                <branch>
                  <attribute name="name" value="Komplexzahn-Gleithörnchen"/>
                </branch>
              </branch>
            </branch>
          </branch>
          <branch>
            <attribute name="name" value="Riesenhörnchen"/>
          </branch>
          <branch>
            <attribute name="name" value="Neuweltliches Kleinsthörnchen"/>
          </branch>
        </branch>
      </branch>
      <branch>
        <attribute name="name" value="Bilche"/>
      </branch>
    </branch>
    <branch>
      <attribute name="name" value="Stachelschweinverwandte"/>
      <branch>
        <attribute name="name" value="Kammfinger"/>
      </branch>
      <branch>
        <attribute name="name" value="Hystricognathi"/>
        <branch>
          <attribute name="name" value="Felsenratte"/>
        </branch>
        <branch>
          <attribute name="name" value="Sandgräber"/>
        </branch>
        <branch>
          <attribute name="name" value="Stachelschweine"/>
        </branch>
        <branch>
          <attribute name="name" value="Chinchillas"/>
        </branch>
        <branch>
          <attribute name="name" value="Dinomyidae"/>
        </branch>
        <branch>
          <attribute name="name" value="Meerschweinchen"/>
        </branch>
        <branch>
          <attribute name="name" value="Agutis und Acouchis"/>
        </branch>
        <branch>
          <attribute name="name" value="Pakas"/>
        </branch>
        <branch>
          <attribute name="name" value="Kammratten"/>
        </branch>
        <branch>
          <attribute name="name" value="Trugratten"/>
        </branch>
        <branch>
          <attribute name="name" value="Chinchillaratten"/>
        </branch>
        <branch>
          <attribute name="name" value="Stachelratten"/>
        </branch>
        <branch>
          <attribute name="name" value="Nutria"/>
        </branch>
        <branch>
          <attribute name="name" value="Baumratten"/>
        </branch>
        <branch>
          <attribute name="name" value="Riesenhutias"/>
        </branch>
      </branch>
    </branch>
  </branch>
</tree>